swpy.py
swpy-0.1.2.dist-info/LICENSE
swpy-0.1.2.dist-info/WHEEL
swpy-0.1.2.dist-info/METADATA
swpy-0.1.2.dist-info/RECORD
