Metadata-Version: 2.1
Name: swpy
Version: 0.1.2
Summary: A simple, yet useful stopwatch library.
Home-page: https://github.com/peinan/swpy
License: MIT
Keywords: stopwatch,timer
Author: Peinan ZHANG
Author-email: peinan7@gmail.co.jp
Requires-Python: >=3.6,<4.0
Classifier: License :: OSI Approved :: MIT License
Classifier: Programming Language :: Python :: 3
Classifier: Programming Language :: Python :: 3.6
Classifier: Programming Language :: Python :: 3.7
Project-URL: Repository, https://github.com/peinan/swpy
